agentforge_sdk/__init__.py
agentforge_sdk/base.py
agentforge_sdk/cli.py
agentforge_sdk/validator.py
agentforge_sdk/templates/__init__.py
agentforge_sdk/templates/agentforge.template.json
agentforge_sdk-0.1.4.dist-info/licenses/LICENSE
agentforge_sdk-0.1.4.dist-info/METADATA
agentforge_sdk-0.1.4.dist-info/WHEEL
agentforge_sdk-0.1.4.dist-info/entry_points.txt
agentforge_sdk-0.1.4.dist-info/top_level.txt
agentforge_sdk-0.1.4.dist-info/RECORD
