Metadata-Version: 2.4
Name: agentforge_sdk
Version: 0.1.4
Summary: A plugin-based agent framework with CLI
Author-email: Ostovar <csg53520@gmail.com>
License: MIT
License-File: LICENSE
Requires-Dist: click
Dynamic: license-file
